huaweicloudsdknat/__init__.py
huaweicloudsdknat/v2/__init__.py
huaweicloudsdknat/v2/nat_async_client.py
huaweicloudsdknat/v2/nat_client.py
huaweicloudsdknat/v2/model/__init__.py
huaweicloudsdknat/v2/model/associated_transit_ip.py
huaweicloudsdknat/v2/model/batch_create_delete_nat_gateway_tag_request.py
huaweicloudsdknat/v2/model/batch_create_delete_nat_gateway_tag_response.py
huaweicloudsdknat/v2/model/batch_create_delete_nat_tags_request_body.py
huaweicloudsdknat/v2/model/batch_create_delete_private_nat_tags_request.py
huaweicloudsdknat/v2/model/batch_create_delete_private_nat_tags_response.py
huaweicloudsdknat/v2/model/batch_create_delete_transit_ip_tags_request.py
huaweicloudsdknat/v2/model/batch_create_delete_transit_ip_tags_response.py
huaweicloudsdknat/v2/model/batch_create_delete_transit_subnet_tags_request.py
huaweicloudsdknat/v2/model/batch_create_delete_transit_subnet_tags_response.py
huaweicloudsdknat/v2/model/batch_create_nat_gateway_dnat_rules_request.py
huaweicloudsdknat/v2/model/batch_create_nat_gateway_dnat_rules_request_body.py
huaweicloudsdknat/v2/model/batch_create_nat_gateway_dnat_rules_response.py
huaweicloudsdknat/v2/model/batch_operate_resource_tags_request_body.py
huaweicloudsdknat/v2/model/creat_transit_ip_option.py
huaweicloudsdknat/v2/model/create_nat_gateway_dnat_option.py
huaweicloudsdknat/v2/model/create_nat_gateway_dnat_rule_option.py
huaweicloudsdknat/v2/model/create_nat_gateway_dnat_rule_request.py
huaweicloudsdknat/v2/model/create_nat_gateway_dnat_rule_response.py
huaweicloudsdknat/v2/model/create_nat_gateway_option.py
huaweicloudsdknat/v2/model/create_nat_gateway_request.py
huaweicloudsdknat/v2/model/create_nat_gateway_request_body.py
huaweicloudsdknat/v2/model/create_nat_gateway_response.py
huaweicloudsdknat/v2/model/create_nat_gateway_snat_rule_option.py
huaweicloudsdknat/v2/model/create_nat_gateway_snat_rule_request.py
huaweicloudsdknat/v2/model/create_nat_gateway_snat_rule_request_option.py
huaweicloudsdknat-3.1.184.dist-info/METADATA
huaweicloudsdknat-3.1.184.dist-info/WHEEL
huaweicloudsdknat-3.1.184.dist-info/licenses/LICENSE
huaweicloudsdknat-3.1.184.dist-info/RECORD
